.coveragerc
AUTHORS
ChangeLog
LICENSE
README.md
requirements.txt
setup.cfg
setup.py
test-requirements.txt
tox.ini
lsf/__init__.py
lsf/bindings.py
lsf/exceptions.py
lsf/job.py
lsf/options.py
lsf/request.py
lsf/rlimits.py
lsf.egg-info/PKG-INFO
lsf.egg-info/SOURCES.txt
lsf.egg-info/dependency_links.txt
lsf.egg-info/not-zip-safe
lsf.egg-info/requires.txt
lsf.egg-info/top_level.txt
tests/__init__.py
tests/test_bindings.py
tests/test_job.py
tests/test_options.py
tests/test_request.py
tests/test_rlimits.py