Metadata-Version: 1.0
Name: lsf
Version: v0.1.0
Summary: A simple interface to LSF.
Home-page: https://github.com/mark-burnett/lsf-python
Author: Mark Burnett
Author-email: mburnett@genome.wustl.edu
License: UNKNOWN
Platform: UNKNOWN
